pulumi_minio/__init__.py
pulumi_minio/_inputs.py
pulumi_minio/_utilities.py
pulumi_minio/get_iam_policy_document.py
pulumi_minio/iam_group.py
pulumi_minio/iam_group_membership.py
pulumi_minio/iam_group_policy.py
pulumi_minio/iam_group_policy_attachment.py
pulumi_minio/iam_group_user_attachment.py
pulumi_minio/iam_policy.py
pulumi_minio/iam_service_account.py
pulumi_minio/iam_user.py
pulumi_minio/iam_user_policy_attachment.py
pulumi_minio/ilm_policy.py
pulumi_minio/kms_key.py
pulumi_minio/outputs.py
pulumi_minio/provider.py
pulumi_minio/pulumi-plugin.json
pulumi_minio/py.typed
pulumi_minio/s3_bucket.py
pulumi_minio/s3_bucket_notification.py
pulumi_minio/s3_bucket_policy.py
pulumi_minio/s3_bucket_server_side_encryption.py
pulumi_minio/s3_bucket_versioning.py
pulumi_minio/s3_object.py
pulumi_minio/config/__init__.py
pulumi_minio/config/__init__.pyi
pulumi_minio/config/vars.py
pulumi_minio-0.16.7.dist-info/METADATA
pulumi_minio-0.16.7.dist-info/WHEEL
pulumi_minio-0.16.7.dist-info/top_level.txt
pulumi_minio-0.16.7.dist-info/RECORD
